[
    {
      "name": "edition_1",
      "dateTime": "2021-12-13T14:52:11.306Z",
      "attibutes": [
        {
          "name": "corner",
          "layer_id": 1,
          "elements": [
            "1.png",
            "10.png",
            "2.png",
            "3.png",
            "4.png",
            "5.png",
            "6.png",
            "7.png",
            "8.png",
            "9.png"
          ],
          "elements_count": 10,
          "position": {
            "x": 0,
            "y": 0
          },
          "size": {
            "width": 1000,
            "height": 1000
          }
        },
        {
          "name": "middle",
          "layer_id": 2,
          "elements": [
            "1.png",
            "10.png",
            "2.png",
            "3.png",
            "4.png",
            "5.png",
            "6.png",
            "7.png",
            "8.png",
            "9.png"
          ],
          "elements_count": 10,
          "position": {
            "x": 0,
            "y": 0
          },
          "size": {
            "width": 1000,
            "height": 1000
          }
        },
        {
          "name": "perpendicular",
          "layer_id": 3,
          "elements": [
            "1.png",
            "10.png",
            "2.png",
            "3.png",
            "4.png",
            "5.png",
            "6.png",
            "7.png",
            "8.png",
            "9.png"
          ],
          "elements_count": 10,
          "position": {
            "x": 0,
            "y": 0
          },
          "size": {
            "width": 1000,
            "height": 1000
          }
        }
      ]
    },
    {
      "name": "edition_2",
      "dateTime": "2021-12-13T14:52:11.349Z",
      "attibutes": [
        {
          "name": "corner",
          "layer_id": 1,
          "elements": [
            "1.png",
            "10.png",
            "2.png",
            "3.png",
            "4.png",
            "5.png",
            "6.png",
            "7.png",
            "8.png",
            "9.png"
          ],
          "elements_count": 10,
          "position": {
            "x": 0,
            "y": 0
          },
          "size": {
            "width": 1000,
            "height": 1000
          }
        },
        {
          "name": "middle",
          "layer_id": 2,
          "elements": [
            "1.png",
            "10.png",
            "2.png",
            "3.png",
            "4.png",
            "5.png",
            "6.png",
            "7.png",
            "8.png",
            "9.png"
          ],
          "elements_count": 10,
          "position": {
            "x": 0,
            "y": 0
          },
          "size": {
            "width": 1000,
            "height": 1000
          }
        },
        {
          "name": "perpendicular",
          "layer_id": 3,
          "elements": [
            "1.png",
            "10.png",
            "2.png",
            "3.png",
            "4.png",
            "5.png",
            "6.png",
            "7.png",
            "8.png",
            "9.png"
          ],
          "elements_count": 10,
          "position": {
            "x": 0,
            "y": 0
          },
          "size": {
            "width": 1000,
            "height": 1000
          }
        }
      ]
    },
    {
      "name": "edition_3",
      "dateTime": "2021-12-13T14:52:11.396Z",
      "attibutes": [
        {
          "name": "corner",
          "layer_id": 1,
          "elements": [
            "1.png",
            "10.png",
            "2.png",
            "3.png",
            "4.png",
            "5.png",
            "6.png",
            "7.png",
            "8.png",
            "9.png"
          ],
          "elements_count": 10,
          "position": {
            "x": 0,
            "y": 0
          },
          "size": {
            "width": 1000,
            "height": 1000
          }
        },
        {
          "name": "middle",
          "layer_id": 2,
          "elements": [
            "1.png",
            "10.png",
            "2.png",
            "3.png",
            "4.png",
            "5.png",
            "6.png",
            "7.png",
            "8.png",
            "9.png"
          ],
          "elements_count": 10,
          "position": {
            "x": 0,
            "y": 0
          },
          "size": {
            "width": 1000,
            "height": 1000
          }
        },
        {
          "name": "perpendicular",
          "layer_id": 3,
          "elements": [
            "1.png",
            "10.png",
            "2.png",
            "3.png",
            "4.png",
            "5.png",
            "6.png",
            "7.png",
            "8.png",
            "9.png"
          ],
          "elements_count": 10,
          "position": {
            "x": 0,
            "y": 0
          },
          "size": {
            "width": 1000,
            "height": 1000
          }
        }
      ]
    },
    {
      "name": "edition_4",
      "dateTime": "2021-12-13T14:52:11.443Z",
      "attibutes": [
        {
          "name": "corner",
          "layer_id": 1,
          "elements": [
            "1.png",
            "10.png",
            "2.png",
            "3.png",
            "4.png",
            "5.png",
            "6.png",
            "7.png",
            "8.png",
            "9.png"
          ],
          "elements_count": 10,
          "position": {
            "x": 0,
            "y": 0
          },
          "size": {
            "width": 1000,
            "height": 1000
          }
        },
        {
          "name": "middle",
          "layer_id": 2,
          "elements": [
            "1.png",
            "10.png",
            "2.png",
            "3.png",
            "4.png",
            "5.png",
            "6.png",
            "7.png",
            "8.png",
            "9.png"
          ],
          "elements_count": 10,
          "position": {
            "x": 0,
            "y": 0
          },
          "size": {
            "width": 1000,
            "height": 1000
          }
        },
        {
          "name": "perpendicular",
          "layer_id": 3,
          "elements": [
            "1.png",
            "10.png",
            "2.png",
            "3.png",
            "4.png",
            "5.png",
            "6.png",
            "7.png",
            "8.png",
            "9.png"
          ],
          "elements_count": 10,
          "position": {
            "x": 0,
            "y": 0
          },
          "size": {
            "width": 1000,
            "height": 1000
          }
        }
      ]
    },
    {
      "name": "edition_5",
      "dateTime": "2021-12-13T14:52:11.493Z",
      "attibutes": [
        {
          "name": "corner",
          "layer_id": 1,
          "elements": [
            "1.png",
            "10.png",
            "2.png",
            "3.png",
            "4.png",
            "5.png",
            "6.png",
            "7.png",
            "8.png",
            "9.png"
          ],
          "elements_count": 10,
          "position": {
            "x": 0,
            "y": 0
          },
          "size": {
            "width": 1000,
            "height": 1000
          }
        },
        {
          "name": "middle",
          "layer_id": 2,
          "elements": [
            "1.png",
            "10.png",
            "2.png",
            "3.png",
            "4.png",
            "5.png",
            "6.png",
            "7.png",
            "8.png",
            "9.png"
          ],
          "elements_count": 10,
          "position": {
            "x": 0,
            "y": 0
          },
          "size": {
            "width": 1000,
            "height": 1000
          }
        },
        {
          "name": "perpendicular",
          "layer_id": 3,
          "elements": [
            "1.png",
            "10.png",
            "2.png",
            "3.png",
            "4.png",
            "5.png",
            "6.png",
            "7.png",
            "8.png",
            "9.png"
          ],
          "elements_count": 10,
          "position": {
            "x": 0,
            "y": 0
          },
          "size": {
            "width": 1000,
            "height": 1000
          }
        }
      ]
    },
    {
      "name": "edition_6",
      "dateTime": "2021-12-13T14:52:11.552Z",
      "attibutes": [
        {
          "name": "corner",
          "layer_id": 1,
          "elements": [
            "1.png",
            "10.png",
            "2.png",
            "3.png",
            "4.png",
            "5.png",
            "6.png",
            "7.png",
            "8.png",
            "9.png"
          ],
          "elements_count": 10,
          "position": {
            "x": 0,
            "y": 0
          },
          "size": {
            "width": 1000,
            "height": 1000
          }
        },
        {
          "name": "middle",
          "layer_id": 2,
          "elements": [
            "1.png",
            "10.png",
            "2.png",
            "3.png",
            "4.png",
            "5.png",
            "6.png",
            "7.png",
            "8.png",
            "9.png"
          ],
          "elements_count": 10,
          "position": {
            "x": 0,
            "y": 0
          },
          "size": {
            "width": 1000,
            "height": 1000
          }
        },
        {
          "name": "perpendicular",
          "layer_id": 3,
          "elements": [
            "1.png",
            "10.png",
            "2.png",
            "3.png",
            "4.png",
            "5.png",
            "6.png",
            "7.png",
            "8.png",
            "9.png"
          ],
          "elements_count": 10,
          "position": {
            "x": 0,
            "y": 0
          },
          "size": {
            "width": 1000,
            "height": 1000
          }
        }
      ]
    },
    {
      "name": "edition_7",
      "dateTime": "2021-12-13T14:52:11.592Z",
      "attibutes": [
        {
          "name": "corner",
          "layer_id": 1,
          "elements": [
            "1.png",
            "10.png",
            "2.png",
            "3.png",
            "4.png",
            "5.png",
            "6.png",
            "7.png",
            "8.png",
            "9.png"
          ],
          "elements_count": 10,
          "position": {
            "x": 0,
            "y": 0
          },
          "size": {
            "width": 1000,
            "height": 1000
          }
        },
        {
          "name": "middle",
          "layer_id": 2,
          "elements": [
            "1.png",
            "10.png",
            "2.png",
            "3.png",
            "4.png",
            "5.png",
            "6.png",
            "7.png",
            "8.png",
            "9.png"
          ],
          "elements_count": 10,
          "position": {
            "x": 0,
            "y": 0
          },
          "size": {
            "width": 1000,
            "height": 1000
          }
        },
        {
          "name": "perpendicular",
          "layer_id": 3,
          "elements": [
            "1.png",
            "10.png",
            "2.png",
            "3.png",
            "4.png",
            "5.png",
            "6.png",
            "7.png",
            "8.png",
            "9.png"
          ],
          "elements_count": 10,
          "position": {
            "x": 0,
            "y": 0
          },
          "size": {
            "width": 1000,
            "height": 1000
          }
        }
      ]
    },
    {
      "name": "edition_8",
      "dateTime": "2021-12-13T14:52:11.628Z",
      "attibutes": [
        {
          "name": "corner",
          "layer_id": 1,
          "elements": [
            "1.png",
            "10.png",
            "2.png",
            "3.png",
            "4.png",
            "5.png",
            "6.png",
            "7.png",
            "8.png",
            "9.png"
          ],
          "elements_count": 10,
          "position": {
            "x": 0,
            "y": 0
          },
          "size": {
            "width": 1000,
            "height": 1000
          }
        },
        {
          "name": "middle",
          "layer_id": 2,
          "elements": [
            "1.png",
            "10.png",
            "2.png",
            "3.png",
            "4.png",
            "5.png",
            "6.png",
            "7.png",
            "8.png",
            "9.png"
          ],
          "elements_count": 10,
          "position": {
            "x": 0,
            "y": 0
          },
          "size": {
            "width": 1000,
            "height": 1000
          }
        },
        {
          "name": "perpendicular",
          "layer_id": 3,
          "elements": [
            "1.png",
            "10.png",
            "2.png",
            "3.png",
            "4.png",
            "5.png",
            "6.png",
            "7.png",
            "8.png",
            "9.png"
          ],
          "elements_count": 10,
          "position": {
            "x": 0,
            "y": 0
          },
          "size": {
            "width": 1000,
            "height": 1000
          }
        }
      ]
    },
    {
      "name": "edition_9",
      "dateTime": "2021-12-13T14:52:11.669Z",
      "attibutes": [
        {
          "name": "corner",
          "layer_id": 1,
          "elements": [
            "1.png",
            "10.png",
            "2.png",
            "3.png",
            "4.png",
            "5.png",
            "6.png",
            "7.png",
            "8.png",
            "9.png"
          ],
          "elements_count": 10,
          "position": {
            "x": 0,
            "y": 0
          },
          "size": {
            "width": 1000,
            "height": 1000
          }
        },
        {
          "name": "middle",
          "layer_id": 2,
          "elements": [
            "1.png",
            "10.png",
            "2.png",
            "3.png",
            "4.png",
            "5.png",
            "6.png",
            "7.png",
            "8.png",
            "9.png"
          ],
          "elements_count": 10,
          "position": {
            "x": 0,
            "y": 0
          },
          "size": {
            "width": 1000,
            "height": 1000
          }
        },
        {
          "name": "perpendicular",
          "layer_id": 3,
          "elements": [
            "1.png",
            "10.png",
            "2.png",
            "3.png",
            "4.png",
            "5.png",
            "6.png",
            "7.png",
            "8.png",
            "9.png"
          ],
          "elements_count": 10,
          "position": {
            "x": 0,
            "y": 0
          },
          "size": {
            "width": 1000,
            "height": 1000
          }
        }
      ]
    },
    {
      "name": "edition_10",
      "dateTime": "2021-12-13T14:52:11.711Z",
      "attibutes": [
        {
          "name": "corner",
          "layer_id": 1,
          "elements": [
            "1.png",
            "10.png",
            "2.png",
            "3.png",
            "4.png",
            "5.png",
            "6.png",
            "7.png",
            "8.png",
            "9.png"
          ],
          "elements_count": 10,
          "position": {
            "x": 0,
            "y": 0
          },
          "size": {
            "width": 1000,
            "height": 1000
          }
        },
        {
          "name": "middle",
          "layer_id": 2,
          "elements": [
            "1.png",
            "10.png",
            "2.png",
            "3.png",
            "4.png",
            "5.png",
            "6.png",
            "7.png",
            "8.png",
            "9.png"
          ],
          "elements_count": 10,
          "position": {
            "x": 0,
            "y": 0
          },
          "size": {
            "width": 1000,
            "height": 1000
          }
        },
        {
          "name": "perpendicular",
          "layer_id": 3,
          "elements": [
            "1.png",
            "10.png",
            "2.png",
            "3.png",
            "4.png",
            "5.png",
            "6.png",
            "7.png",
            "8.png",
            "9.png"
          ],
          "elements_count": 10,
          "position": {
            "x": 0,
            "y": 0
          },
          "size": {
            "width": 1000,
            "height": 1000
          }
        }
      ]
    },
    {
      "name": "edition_11",
      "dateTime": "2021-12-13T14:52:11.756Z",
      "attibutes": [
        {
          "name": "corner",
          "layer_id": 1,
          "elements": [
            "1.png",
            "10.png",
            "2.png",
            "3.png",
            "4.png",
            "5.png",
            "6.png",
            "7.png",
            "8.png",
            "9.png"
          ],
          "elements_count": 10,
          "position": {
            "x": 0,
            "y": 0
          },
          "size": {
            "width": 1000,
            "height": 1000
          }
        },
        {
          "name": "middle",
          "layer_id": 2,
          "elements": [
            "1.png",
            "10.png",
            "2.png",
            "3.png",
            "4.png",
            "5.png",
            "6.png",
            "7.png",
            "8.png",
            "9.png"
          ],
          "elements_count": 10,
          "position": {
            "x": 0,
            "y": 0
          },
          "size": {
            "width": 1000,
            "height": 1000
          }
        },
        {
          "name": "perpendicular",
          "layer_id": 3,
          "elements": [
            "1.png",
            "10.png",
            "2.png",
            "3.png",
            "4.png",
            "5.png",
            "6.png",
            "7.png",
            "8.png",
            "9.png"
          ],
          "elements_count": 10,
          "position": {
            "x": 0,
            "y": 0
          },
          "size": {
            "width": 1000,
            "height": 1000
          }
        }
      ]
    }
  ]